day4mooresm/moore.v
module seq_det_11_moore(input clk, reset, din, output reg dout);
 parameter S0=0,S1=1,S2=2;
 reg [1:0] state;
 always @(posedge clk or reset)
   begin
   if(reset) begin
     state<=50;
        dout<=0;
   end else begin 
     case(state)
      S0: begin
        dout <= 1'b0;  
      if(din)
        state<=S1;
      else
        state<=S0;
      end
     S1:begin
       if(din) begin
         state<=S2; dout<=1'b1;
       end else begin
         state<=S0; dout<=1'b0;
      end
     end
     S2:begin
       if(din) begin
         state<=S2; dout<=1'b1;
       end else begin
         state<=S0; dout<=1'b0;
      end
     end
     default: begin
       dout<=0; state<=50;
     end
    endcase
    end
    end
endmodule

day4mooresm/moore_tb.v
module seq_det_11_moore_tb;  
   reg clk, reset, in;
   wire out; integer i;
   

   seq_det_11_moore DUT(clk, reset, in, out);
   initial
     forever #5 clk=~clk;
   
   initial begin
     reset = 1'b1; clk=1'b0; in=0;
     #5
     reset = 1'b0;
     for(i=0;i<100;i=i+1) begin
       @(posedge clk);#1;
       in = $random;
       if(out==1'b1)
         $display("PASS:Sequence 11 detected\n");
       end
       #50;$finish;
      end
    
    initial begin
           $dumpfile("dump.vcd");
           $dumpvars;
      end
endmodule

day4mooresm/dump.vcd
$date
    Mar 26, 2026  11:28:30
$end
$version
    TOOL:	xmsim(64)	20.09-s012
$end
$timescale
    1 ns
$end

$scope module seq_det_11_moore_tb $end
$var reg       1 !    clk $end
$var reg       1 "    reset $end
$var reg       1 #    in $end
$var wire      1 $    out  $end
$var integer  32 %    i $end

$scope module DUT $end
$var wire      1 &    clk  $end
$var wire      1 '    reset  $end
$var wire      1 (    din  $end
$var reg       1 )    dout $end
$var parameter 32 *    S0 $end
$var parameter 32 +    S1 $end
$var parameter 32 ,    S2 $end
$var reg       2 -    state [1:0] $end
$upscope $end

$upscope $end

$enddefinitions $end
$dumpvars
b10 ,
b1 +
b0 *
0!
1"
0#
0$
bx %
0&
1'
0(
0)
b10 -
$end
#5
1!
0"
b0 %
0'
1&
b0 -
#10
0!
0&
#15
1!
1&
#16
b1 %
#20
0!
0&
#25
1!
1&
#26
1#
b10 %
1(
#30
0!
0&
#35
1!
1&
b1 -
#36
b11 %
#40
0!
0&
#45
1!
1&
b10 -
1)
1$
#46
b100 %
#50
0!
0&
#55
1!
1&
#56
b101 %
#60
0!
0&
#65
1!
1&
#66
b110 %
#70
0!
0&
#75
1!
1&
#76
b111 %
#80
0!
0&
#85
1!
1&
#86
0#
b1000 %
0(
#90
0!
0&
#95
1!
1&
b0 -
0)
0$
#96
1#
b1001 %
1(
#100
0!
0&
#105
1!
1&
b1 -
#106
b1010 %
#110
0!
0&
#115
1!
1&
b10 -
1)
1$
#116
0#
b1011 %
0(
#120
0!
0&
#125
1!
1&
b0 -
0)
0$
#126
1#
b1100 %
1(
#130
0!
0&
#135
1!
1&
b1 -
#136
b1101 %
#140
0!
0&
#145
1!
1&
b10 -
1)
1$
#146
0#
b1110 %
0(
#150
0!
0&
#155
1!
1&
b0 -
0)
0$
#156
1#
b1111 %
1(
#160
0!
0&
#165
1!
1&
b1 -
#166
0#
b10000 %
0(
#170
0!
0&
#175
1!
1&
b0 -
#176
1#
b10001 %
1(
#180
0!
0&
#185
1!
1&
b1 -
#186
0#
b10010 %
0(
#190
0!
0&
#195
1!
1&
b0 -
#196
1#
b10011 %
1(
#200
0!
0&
#205
1!
1&
b1 -
#206
b10100 %
#210
0!
0&
#215
1!
1&
b10 -
1)
1$
#216
0#
b10101 %
0(
#220
0!
0&
#225
1!
1&
b0 -
0)
0$
#226
1#
b10110 %
1(
#230
0!
0&
#235
1!
1&
b1 -
#236
0#
b10111 %
0(
#240
0!
0&
#245
1!
1&
b0 -
#246
b11000 %
#250
0!
0&
#255
1!
1&
#256
b11001 %
#260
0!
0&
#265
1!
1&
#266
1#
b11010 %
1(
#270
0!
0&
#275
1!
1&
b1 -
#276
0#
b11011 %
0(
#280
0!
0&
#285
1!
1&
b0 -
#286
1#
b11100 %
1(
#290
0!
0&
#295
1!
1&
b1 -
#296
b11101 %
#300
0!
0&
#305
1!
1&
b10 -
1)
1$
#306
b11110 %
#310
0!
0&
#315
1!
1&
#316
b11111 %
#320
0!
0&
#325
1!
1&
#326
0#
b100000 %
0(
#330
0!
0&
#335
1!
1&
b0 -
0)
0$
#336
b100001 %
#340
0!
0&
#345
1!
1&
#346
b100010 %
#350
0!
0&
#355
1!
1&
#356
b100011 %
#360
0!
0&
#365
1!
1&
#366
1#
b100100 %
1(
#370
0!
0&
#375
1!
1&
b1 -
#376
0#
b100101 %
0(
#380
0!
0&
#385
1!
1&
b0 -
#386
1#
b100110 %
1(
#390
0!
0&
#395
1!
1&
b1 -
#396
b100111 %
#400
0!
0&
#405
1!
1&
b10 -
1)
1$
#406
b101000 %
#410
0!
0&
#415
1!
1&
#416
b101001 %
#420
0!
0&
#425
1!
1&
#426
b101010 %
#430
0!
0&
#435
1!
1&
#436
0#
b101011 %
0(
#440
0!
0&
#445
1!
1&
b0 -
0)
0$
#446
b101100 %
#450
0!
0&
#455
1!
1&
#456
1#
b101101 %
1(
#460
0!
0&
#465
1!
1&
b1 -
#466
b101110 %
#470
0!
0&
#475
1!
1&
b10 -
1)
1$
#476
b101111 %
#480
0!
0&
#485
1!
1&
#486
0#
b110000 %
0(
#490
0!
0&
#495
1!
1&
b0 -
0)
0$
#496
b110001 %
#500
0!
0&
#505
1!
1&
#506
b110010 %
#510
0!
0&
#515
1!
1&
#516
b110011 %
#520
0!
0&
#525
1!
1&
#526
b110100 %
#530
0!
0&
#535
1!
1&
#536
1#
b110101 %
1(
#540
0!
0&
#545
1!
1&
b1 -
#546
0#
b110110 %
0(
#550
0!
0&
#555
1!
1&
b0 -
#556
b110111 %
#560
0!
0&
#565
1!
1&
#566
1#
b111000 %
1(
#570
0!
0&
#575
1!
1&
b1 -
#576
b111001 %
#580
0!
0&
#585
1!
1&
b10 -
1)
1$
#586
0#
b111010 %
0(
#590
0!
0&
#595
1!
1&
b0 -
0)
0$
#596
b111011 %
#600
0!
0&
#605
1!
1&
#606
b111100 %
#610
0!
0&
#615
1!
1&
#616
b111101 %
#620
0!
0&
#625
1!
1&
#626
b111110 %
#630
0!
0&
#635
1!
1&
#636
1#
b111111 %
1(
#640
0!
0&
#645
1!
1&
b1 -
#646
b1000000 %
#650
0!
0&
#655
1!
1&
b10 -
1)
1$
#656
b1000001 %
#660
0!
0&
#665
1!
1&
#666
b1000010 %
#670
0!
0&
#675
1!
1&
#676
b1000011 %
#680
0!
0&
#685
1!
1&
#686
0#
b1000100 %
0(
#690
0!
0&
#695
1!
1&
b0 -
0)
0$
#696
b1000101 %
#700
0!
0&
#705
1!
1&
#706
1#
b1000110 %
1(
#710
0!
0&
#715
1!
1&
b1 -
#716
b1000111 %
#720
0!
0&
#725
1!
1&
b10 -
1)
1$
#726
b1001000 %
#730
0!
0&
#735
1!
1&
#736
0#
b1001001 %
0(
#740
0!
0&
#745
1!
1&
b0 -
0)
0$
#746
b1001010 %
#750
0!
0&
#755
1!
1&
#756
1#
b1001011 %
1(
#760
0!
0&
#765
1!
1&
b1 -
#766
b1001100 %
#770
0!
0&
#775
1!
1&
b10 -
1)
1$
#776
0#
b1001101 %
0(
#780
0!
0&
#785
1!
1&
b0 -
0)
0$
#786
1#
b1001110 %
1(
#790
0!
0&
#795
1!
1&
b1 -
#796
b1001111 %
#800
0!
0&
#805
1!
1&
b10 -
1)
1$
#806
0#
b1010000 %
0(
#810
0!
0&
#815
1!
1&
b0 -
0)
0$
#816
1#
b1010001 %
1(
#820
0!
0&
#825
1!
1&
b1 -
#826
b1010010 %
#830
0!
0&
#835
1!
1&
b10 -
1)
1$
#836
b1010011 %
#840
0!
0&
#845
1!
1&
#846
0#
b1010100 %
0(
#850
0!
0&
#855
1!
1&
b0 -
0)
0$
#856
1#
b1010101 %
1(
#860
0!
0&
#865
1!
1&
b1 -
#866
b1010110 %
#870
0!
0&
#875
1!
1&
b10 -
1)
1$
#876
0#
b1010111 %
0(
#880
0!
0&
#885
1!
1&
b0 -
0)
0$
#886
b1011000 %
#890
0!
0&
#895
1!
1&
#896
b1011001 %
#900
0!
0&
#905
1!
1&
#906
b1011010 %
#910
0!
0&
#915
1!
1&
#916
1#
b1011011 %
1(
#920
0!
0&
#925
1!
1&
b1 -
#926
b1011100 %
#930
0!
0&
#935
1!
1&
b10 -
1)
1$
#936
0#
b1011101 %
0(
#940
0!
0&
#945
1!
1&
b0 -
0)
0$
#946
b1011110 %
#950
0!
0&
#955
1!
1&
#956
1#
b1011111 %
1(
#960
0!
0&
#965
1!
1&
b1 -
#966
b1100000 %
#970
0!
0&
#975
1!
1&
b10 -
1)
1$
#976
b1100001 %
#980
0!
0&
#985
1!
1&
#986
b1100010 %
#990
0!
0&
#995
1!
1&
#996
b1100011 %
#1000
0!
0&
#1005
1!
1&
#1006
0#
b1100100 %
0(
#1010
0!
0&
#1015
1!
1&
b0 -
0)
0$
