day4meally/mealy.v
//mealy circuit for detecting sequence 11.
module seq_det_11_mealy(input clk, reset, din,
      output reg dout);
      parameter S0 = 0, S1=1;
      reg[1:0] state, next_state;
     //state transition
     always @(posedge clk or reset)
     begin
      if(reset)
          state<=S0;
      else
         state<= next_state;
      end
//stae machine coding
      always @(state or din)
      begin 
        case(state)
          S0: begin
           dout <= 1'b0;
           if(din)
            next_state <= S1;
           else
            next_state <= S0;
         end
         S1: begin
           if(din) begin
            next_state <= S1;
             dout <= 1'b1;
           end else begin
            next_state <= S0;
            dout <= 1'b0;
         end
         end
       default:begin
      dout<=0;
       end
    endcase
  end
endmodule

day4meally/mealy_tb.v
module seq_det_11_mealy_tb;  
   reg clk, reset, in;
   wire out; 
   integer i;
   

   seq_det_11_mealy DUT(clk, reset, in, out);
   initial
     forever #5 clk=~clk;
   
   initial begin
     reset = 1'b1; clk=1'b0; in=0;
     #5
     reset = 1'b0;
     for(i=0;i<100;i=i+1) begin
       @(negedge clk);
       in = $random;
       if(out==1'b1)
         $display("PASS:Sequence 11 detected\n");
       end
       #50;$finish;
      end
    //dump
    initial begin
           $dumpfile("dump.vcd");
           $dumpvars;
      end
endmodule

day4meally/dump.vcd
$date
    Mar 26, 2026  13:03:26
$end
$version
    TOOL:	xmsim(64)	20.09-s012
$end
$timescale
    1 ns
$end

$scope module seq_det_11_mealy_tb $end
$var reg       1 !    clk $end
$var reg       1 "    reset $end
$var reg       1 #    in $end
$var wire      1 $    out  $end
$var integer  32 %    i $end

$scope module DUT $end
$var wire      1 &    clk  $end
$var wire      1 '    reset  $end
$var wire      1 (    din  $end
$var reg       1 )    dout $end
$var parameter 32 *    S0 $end
$var parameter 32 +    S1 $end
$var reg       2 ,    state [1:0] $end
$var reg       2 -    next_state [1:0] $end
$upscope $end

$upscope $end

$enddefinitions $end
$dumpvars
b1 +
b0 *
0!
1"
0#
0$
bx %
0&
1'
0(
0)
b0 ,
b0 -
$end
#5
1!
0"
b0 %
0'
1&
#10
0!
b1 %
0&
#15
1!
1&
#20
0!
1#
b10 %
1(
0&
b1 -
#25
1!
1&
b1 ,
1)
1$
#30
0!
b11 %
0&
#35
1!
1&
#40
0!
b100 %
0&
#45
1!
1&
#50
0!
b101 %
0&
#55
1!
1&
#60
0!
b110 %
0&
#65
1!
1&
#70
0!
b111 %
0&
#75
1!
1&
#80
0!
0#
b1000 %
0(
0&
b0 -
0)
0$
#85
1!
1&
b0 ,
#90
0!
1#
b1001 %
1(
0&
b1 -
#95
1!
1&
b1 ,
1)
1$
#100
0!
b1010 %
0&
#105
1!
1&
#110
0!
0#
b1011 %
0(
0&
b0 -
0)
0$
#115
1!
1&
b0 ,
#120
0!
1#
b1100 %
1(
0&
b1 -
#125
1!
1&
b1 ,
1)
1$
#130
0!
b1101 %
0&
#135
1!
1&
#140
0!
0#
b1110 %
0(
0&
b0 -
0)
0$
#145
1!
1&
b0 ,
#150
0!
1#
b1111 %
1(
0&
b1 -
#155
1!
1&
b1 ,
1)
1$
#160
0!
0#
b10000 %
0(
0&
b0 -
0)
0$
#165
1!
1&
b0 ,
#170
0!
1#
b10001 %
1(
0&
b1 -
#175
1!
1&
b1 ,
1)
1$
#180
0!
0#
b10010 %
0(
0&
b0 -
0)
0$
#185
1!
1&
b0 ,
#190
0!
1#
b10011 %
1(
0&
b1 -
#195
1!
1&
b1 ,
1)
1$
#200
0!
b10100 %
0&
#205
1!
1&
#210
0!
0#
b10101 %
0(
0&
b0 -
0)
0$
#215
1!
1&
b0 ,
#220
0!
1#
b10110 %
1(
0&
b1 -
#225
1!
1&
b1 ,
1)
1$
#230
0!
0#
b10111 %
0(
0&
b0 -
0)
0$
#235
1!
1&
b0 ,
#240
0!
b11000 %
0&
#245
1!
1&
#250
0!
b11001 %
0&
#255
1!
1&
#260
0!
1#
b11010 %
1(
0&
b1 -
#265
1!
1&
b1 ,
1)
1$
#270
0!
0#
b11011 %
0(
0&
b0 -
0)
0$
#275
1!
1&
b0 ,
#280
0!
1#
b11100 %
1(
0&
b1 -
#285
1!
1&
b1 ,
1)
1$
#290
0!
b11101 %
0&
#295
1!
1&
#300
0!
b11110 %
0&
#305
1!
1&
#310
0!
b11111 %
0&
#315
1!
1&
#320
0!
0#
b100000 %
0(
0&
b0 -
0)
0$
#325
1!
1&
b0 ,
#330
0!
b100001 %
0&
#335
1!
1&
#340
0!
b100010 %
0&
#345
1!
1&
#350
0!
b100011 %
0&
#355
1!
1&
#360
0!
1#
b100100 %
1(
0&
b1 -
#365
1!
1&
b1 ,
1)
1$
#370
0!
0#
b100101 %
0(
0&
b0 -
0)
0$
#375
1!
1&
b0 ,
#380
0!
1#
b100110 %
1(
0&
b1 -
#385
1!
1&
b1 ,
1)
1$
#390
0!
b100111 %
0&
#395
1!
1&
#400
0!
b101000 %
0&
#405
1!
1&
#410
0!
b101001 %
0&
#415
1!
1&
#420
0!
b101010 %
0&
#425
1!
1&
#430
0!
0#
b101011 %
0(
0&
b0 -
0)
0$
#435
1!
1&
b0 ,
#440
0!
b101100 %
0&
#445
1!
1&
#450
0!
1#
b101101 %
1(
0&
b1 -
#455
1!
1&
b1 ,
1)
1$
#460
0!
b101110 %
0&
#465
1!
1&
#470
0!
b101111 %
0&
#475
1!
1&
#480
0!
0#
b110000 %
0(
0&
b0 -
0)
0$
#485
1!
1&
b0 ,
#490
0!
b110001 %
0&
#495
1!
1&
#500
0!
b110010 %
0&
#505
1!
1&
#510
0!
b110011 %
0&
#515
1!
1&
#520
0!
b110100 %
0&
#525
1!
1&
#530
0!
1#
b110101 %
1(
0&
b1 -
#535
1!
1&
b1 ,
1)
1$
#540
0!
0#
b110110 %
0(
0&
b0 -
0)
0$
#545
1!
1&
b0 ,
#550
0!
b110111 %
0&
#555
1!
1&
#560
0!
1#
b111000 %
1(
0&
b1 -
#565
1!
1&
b1 ,
1)
1$
#570
0!
b111001 %
0&
#575
1!
1&
#580
0!
0#
b111010 %
0(
0&
b0 -
0)
0$
#585
1!
1&
b0 ,
#590
0!
b111011 %
0&
#595
1!
1&
#600
0!
b111100 %
0&
#605
1!
1&
#610
0!
b111101 %
0&
#615
1!
1&
#620
0!
b111110 %
0&
#625
1!
1&
#630
0!
1#
b111111 %
1(
0&
b1 -
#635
1!
1&
b1 ,
1)
1$
#640
0!
b1000000 %
0&
#645
1!
1&
#650
0!
b1000001 %
0&
#655
1!
1&
#660
0!
b1000010 %
0&
#665
1!
1&
#670
0!
b1000011 %
0&
#675
1!
1&
#680
0!
0#
b1000100 %
0(
0&
b0 -
0)
0$
#685
1!
1&
b0 ,
#690
0!
b1000101 %
0&
#695
1!
1&
#700
0!
1#
b1000110 %
1(
0&
b1 -
#705
1!
1&
b1 ,
1)
1$
#710
0!
b1000111 %
0&
#715
1!
1&
#720
0!
b1001000 %
0&
#725
1!
1&
#730
0!
0#
b1001001 %
0(
0&
b0 -
0)
0$
#735
1!
1&
b0 ,
#740
0!
b1001010 %
0&
#745
1!
1&
#750
0!
1#
b1001011 %
1(
0&
b1 -
#755
1!
1&
b1 ,
1)
1$
#760
0!
b1001100 %
0&
#765
1!
1&
#770
0!
0#
b1001101 %
0(
0&
b0 -
0)
0$
#775
1!
1&
b0 ,
#780
0!
1#
b1001110 %
1(
0&
b1 -
#785
1!
1&
b1 ,
1)
1$
#790
0!
b1001111 %
0&
#795
1!
1&
#800
0!
0#
b1010000 %
0(
0&
b0 -
0)
0$
#805
1!
1&
b0 ,
#810
0!
1#
b1010001 %
1(
0&
b1 -
#815
1!
1&
b1 ,
1)
1$
#820
0!
b1010010 %
0&
#825
1!
1&
#830
0!
b1010011 %
0&
#835
1!
1&
#840
0!
0#
b1010100 %
0(
0&
b0 -
0)
0$
#845
1!
1&
b0 ,
#850
0!
1#
b1010101 %
1(
0&
b1 -
#855
1!
1&
b1 ,
1)
1$
#860
0!
b1010110 %
0&
#865
1!
1&
#870
0!
0#
b1010111 %
0(
0&
b0 -
0)
0$
#875
1!
1&
b0 ,
#880
0!
b1011000 %
0&
#885
1!
1&
#890
0!
b1011001 %
0&
#895
1!
1&
#900
0!
b1011010 %
0&
#905
1!
1&
#910
0!
1#
b1011011 %
1(
0&
b1 -
#915
1!
1&
b1 ,
1)
1$
#920
0!
b1011100 %
0&
#925
1!
1&
#930
0!
0#
b1011101 %
0(
0&
b0 -
0)
0$
#935
1!
1&
b0 ,
#940
0!
b1011110 %
0&
#945
1!
1&
#950
0!
1#
b1011111 %
1(
0&
b1 -
#955
1!
1&
b1 ,
1)
1$
#960
0!
b1100000 %
0&
#965
1!
1&
#970
0!
b1100001 %
0&
#975
1!
1&
#980
0!
b1100010 %
0&
#985
1!
1&
#990
0!
b1100011 %
0&
#995
1!
1&
#1000
0!
0#
b1100100 %
0(
0&
b0 -
0)
0$
#1005
1!
1&
b0 ,
