twonum/twonum.v

module seq_detector(input clk, reset, i, output reg out);
parameter S0 = 0, S1=1, S2 = 2, S3=3, S4 = 4; 

reg [2:0] state, next_state;

always @(posedge clk or posedge reset)
begin
 if (reset)
    state <= S0;
 else
    state <= next_state;
end

always @(state or i)
begin 
   case(state)
      S0: begin
       out <= 1'b0;
       if(i)
         next_state <= S1;
       else
         next_state <= S0;
      end    
      S1: begin
       out <= 1'b0;
       if(i)
         next_state <= S1;
       else
         next_state <= S2;
      end            

      S2: begin
       out <= 1'b0;
       if(i)
         next_state <= S4;
       else
         next_state <= S3;
      end        
      S3: begin
       if(i) begin
         next_state <= S1;
         out <= 1'b1;
        end
       else begin
         next_state <= S0;
         out <= 1'b0;
      end        
    end
      S4: begin
       if(i) begin
         next_state <= S1;
         out <= 1'b0;
        end
       else begin
         next_state <= S2;
         out <= 1'b1;
      end        
    end
    default: begin
       next_state <= S0;
       out <= 1'b0;
    end
   endcase
  end
endmodule

twonum/twonum_tb.v
module seq_detector_tb;
 reg clk,reset,x;
 wire out;
 integer i;

seq_detector dut(clk,reset,x,out);
initial 
    forever #5 clk =~ clk;
initial begin
  reset = 1'b1;
  clk = 1'b0;
  x=0;

 #5;
reset = 1'b0;
for (i=0;i<50;i=i+1) begin
  @(posedge clk); #1;
  x= $random;
  end

#20 ; 
$finish;
end 
initial begin
  $dumpfile("dump.vcd");
  $dumpvars;
  end
endmodule

twonum/dump.vcd
$date
    Mar 26, 2026  16:32:30
$end
$version
    TOOL:	xmsim(64)	20.09-s012
$end
$timescale
    1 ns
$end

$scope module seq_detector_tb $end
$var reg       1 !    clk $end
$var reg       1 "    reset $end
$var reg       1 #    x $end
$var wire      1 $    out  $end
$var integer  32 %    i $end

$scope module dut $end
$var wire      1 &    clk  $end
$var wire      1 '    reset  $end
$var wire      1 (    i  $end
$var reg       1 )    out $end
$var parameter 32 *    S0 $end
$var parameter 32 +    S1 $end
$var parameter 32 ,    S2 $end
$var parameter 32 -    S3 $end
$var parameter 32 .    S4 $end
$var reg       3 /    state [2:0] $end
$var reg       3 0    next_state [2:0] $end
$upscope $end

$upscope $end

$enddefinitions $end
$dumpvars
b100 .
b11 -
b10 ,
b1 +
b0 *
0!
1"
0#
0$
bx %
0&
1'
0(
0)
b0 /
b0 0
$end
#5
1!
0"
b0 %
0'
1&
#10
0!
0&
#15
1!
1&
#16
b1 %
#20
0!
0&
#25
1!
1&
#26
1#
b10 %
1(
b1 0
#30
0!
0&
#35
1!
1&
b1 /
#36
b11 %
#40
0!
0&
#45
1!
1&
#46
b100 %
#50
0!
0&
#55
1!
1&
#56
b101 %
#60
0!
0&
#65
1!
1&
#66
b110 %
#70
0!
0&
#75
1!
1&
#76
b111 %
#80
0!
0&
#85
1!
1&
#86
0#
b1000 %
0(
b10 0
#90
0!
0&
#95
1!
1&
b10 /
b11 0
#96
1#
b1001 %
1(
b100 0
#100
0!
0&
#105
1!
1&
b100 /
b1 0
#106
b1010 %
#110
0!
0&
#115
1!
1&
b1 /
#116
0#
b1011 %
0(
b10 0
#120
0!
0&
#125
1!
1&
b10 /
b11 0
#126
1#
b1100 %
1(
b100 0
#130
0!
0&
#135
1!
1&
b100 /
b1 0
#136
b1101 %
#140
0!
0&
#145
1!
1&
b1 /
#146
0#
b1110 %
0(
b10 0
#150
0!
0&
#155
1!
1&
b10 /
b11 0
#156
1#
b1111 %
1(
b100 0
#160
0!
0&
#165
1!
1&
b100 /
b1 0
#166
0#
b10000 %
0(
b10 0
1)
1$
#170
0!
0&
#175
1!
1&
b10 /
0)
b11 0
0$
#176
1#
b10001 %
1(
b100 0
#180
0!
0&
#185
1!
1&
b100 /
b1 0
#186
0#
b10010 %
0(
b10 0
1)
1$
#190
0!
0&
#195
1!
1&
b10 /
0)
b11 0
0$
#196
1#
b10011 %
1(
b100 0
#200
0!
0&
#205
1!
1&
b100 /
b1 0
#206
b10100 %
#210
0!
0&
#215
1!
1&
b1 /
#216
0#
b10101 %
0(
b10 0
#220
0!
0&
#225
1!
1&
b10 /
b11 0
#226
1#
b10110 %
1(
b100 0
#230
0!
0&
#235
1!
1&
b100 /
b1 0
#236
0#
b10111 %
0(
b10 0
1)
1$
#240
0!
0&
#245
1!
1&
b10 /
0)
b11 0
0$
#246
b11000 %
#250
0!
0&
#255
1!
1&
b11 /
b0 0
#256
b11001 %
#260
0!
0&
#265
1!
1&
b0 /
#266
1#
b11010 %
1(
b1 0
#270
0!
0&
#275
1!
1&
b1 /
#276
0#
b11011 %
0(
b10 0
#280
0!
0&
#285
1!
1&
b10 /
b11 0
#286
1#
b11100 %
1(
b100 0
#290
0!
0&
#295
1!
1&
b100 /
b1 0
#296
b11101 %
#300
0!
0&
#305
1!
1&
b1 /
#306
b11110 %
#310
0!
0&
#315
1!
1&
#316
b11111 %
#320
0!
0&
#325
1!
1&
#326
0#
b100000 %
0(
b10 0
#330
0!
0&
#335
1!
1&
b10 /
b11 0
#336
b100001 %
#340
0!
0&
#345
1!
1&
b11 /
b0 0
#346
b100010 %
#350
0!
0&
#355
1!
1&
b0 /
#356
b100011 %
#360
0!
0&
#365
1!
1&
#366
1#
b100100 %
1(
b1 0
#370
0!
0&
#375
1!
1&
b1 /
#376
0#
b100101 %
0(
b10 0
#380
0!
0&
#385
1!
1&
b10 /
b11 0
#386
1#
b100110 %
1(
b100 0
#390
0!
0&
#395
1!
1&
b100 /
b1 0
#396
b100111 %
#400
0!
0&
#405
1!
1&
b1 /
#406
b101000 %
#410
0!
0&
#415
1!
1&
#416
b101001 %
#420
0!
0&
#425
1!
1&
#426
b101010 %
#430
0!
0&
#435
1!
1&
#436
0#
b101011 %
0(
b10 0
#440
0!
0&
#445
1!
1&
b10 /
b11 0
#446
b101100 %
#450
0!
0&
#455
1!
1&
b11 /
b0 0
#456
1#
b101101 %
1(
b1 0
1)
1$
#460
0!
0&
#465
1!
1&
b1 /
0)
0$
#466
b101110 %
#470
0!
0&
#475
1!
1&
#476
b101111 %
#480
0!
0&
#485
1!
1&
#486
0#
b110000 %
0(
b10 0
#490
0!
0&
#495
1!
1&
b10 /
b11 0
#496
b110001 %
#500
0!
0&
#505
1!
1&
b11 /
b0 0
#506
b110010 %
#510
0!
0&
#515
1!
1&
b0 /
